rag_oozsen/__init__.py
rag_oozsen/chat_flow/__init__.py
rag_oozsen/chat_flow/llm_interface.py
rag_oozsen/chat_flow/prompt_handler.py
rag_oozsen/config/config.py
rag_oozsen/config/config.yaml
rag_oozsen/knowledge_base/__init__.py
rag_oozsen/knowledge_base/document_loader.py
rag_oozsen/knowledge_base/text_splitter.py
rag_oozsen/vector_db/__init__.py
rag_oozsen/vector_db/database.py
rag_oozsen/vector_db/query.py
rag_oozsen-0.1.3.dist-info/METADATA
rag_oozsen-0.1.3.dist-info/WHEEL
rag_oozsen-0.1.3.dist-info/entry_points.txt
rag_oozsen-0.1.3.dist-info/top_level.txt
rag_oozsen-0.1.3.dist-info/RECORD
